{
  "seg_id": "SEG_EXEG_1978-10-10_SECTION_016_291",
  "doc_id": "DOC_EXEG_SECTION_016",
  "slug": "1978-10-10-section-016-291",
  "title": "1978-10-10_SECTION_016_291.txt",
  "position": 291,
  "date_start": "1978-10-10",
  "date_end": "1978-10-10",
  "date_display": "October 10, 1978",
  "date_confidence": "exact",
  "date_basis": "chunk_manifest",
  "concise_summary": null,
  "key_claims": null,
  "recurring_concepts": null,
  "people_entities": null,
  "texts_works": null,
  "autobiographical": null,
  "theological_motifs": null,
  "literary_self_ref": null,
  "symbols_images": null,
  "tensions": null,
  "evidence_quotes": null,
  "uncertainty_flags": null,
  "reading_excerpt": null,
  "word_count": 2000,
  "raw_text": "the Christian fish sign that caused me to remember, to cease to forget. That is what it is supposed to do ... counteract the Lie (the delusion). So I combine Indian doctrines of maya with the Judo-Christian etc. idea of the Fall. I say, we fell into Satan's world which is irreal, a \"spurious interpolation.\" Yet God is using Satan, through enantiodromia. Countering him. Reversing him. Here, within this very domain; the good that occurs in this domain (through enantiodromia) is placed into the macrometasomakosmos. Evil is concerted into good by enantiodromia and then inserted into the macrometasomakosmos. The theories about the Fall must be revised; an intellectual error, not moral error, must be presumed. One can almost --almost-- view Satan's activity as a high technology in which the simulation of a world order is achieved. This element of maya or dokos has interested thinkers in India and Greece, but with Christianity and Gnosticism comes a really penetrating analysis between the two elements of world and Satan, with the theme of epistemology running through Gnosticism -- which is why I can't abandon it. We fell asleep because we were induced into falling asleep; the spurious world had to be there for us to take it as real; we ourselves don't generate it... unless it's a maze that we ourselves built and then fell into (which always remains a possibility). Probably the wisest view is to say: the truth --like the Self-is splintered up over thousands of miles and years; bits are found here and there, then and now, and must be re-collected; bits appear in the Greek naturalists, in Pythagoras, in Plato, Parmenides, in Heraclitus, Neo-Platonism, Zoroastrianism, Gnosticism, Taoism, Mani, Gnosticism, orthodox Christianity, Judaism, Brahmanism, Buddhism, Orphism, the other mystery religions. Each religion or philosophy or philosopher contains one or more bits, but the total system interweaves it into falsity, so each as a total system must be rejected, and none is to be accepted at the expense of all the others (e.g. \"I am a Christian\" or \"I follow Mani\"). This alone, in itself, is a fascinating thought: here in our spatiotemporal world we have the truth but it is splintered --exploded like the eide-- over thousands of years and thousands of miles and (as I say) but be recollected, as the Self or Soul or eidos must be. This is my task. {folder 01 - 085} 10-24-80 In that case, each given system is in itself part of the enslaving snare of delusion; in other words, as soon as I avow one philosopher or system (e.g. Spinoza or Schopenhauer or Kant or Anaxagoras or Parmenides or Gnosticism) I have become again or more ensnared, as I am by this spatiotemporal world itself; it is as if the eidos of Truth is exploded and splintered like all the eide. And all the Selves and Souls. But what else could you expect here in realm #4? Since everything real is here only in discrete bits. Of course this means that I can never come up with the whole, true, complete explanation/answer. I can re-collect and re-collect, do better and better, but never completely make unified the eidos of Truth. Yet, in (3-74) when I meta-abstracted, a great deal of the eidos the Truth was revealed to me; however, alas, I did not understand it then and do not yet. Look; I may be on to something here, that in realm #4 it is impossible to re-collect any given eidos including that of a true verbal (informational) picture (analog) of reality; that in fact the true informational analog will be exploded over thousands of miles and thousands of years like all other eide. Such is the situation here in the spatiotemporal realm; this is one of its drawbacks (among many). Fascinating. In that case, no wonder I haven't been able to match my 2-3-74 experience to any religion or any philosopher, yet many seem in part to apply. The truth is splintered! This would explain, too, Why the sacerdotal power is found in bits in, say, the alley; for the same reason: it is exploded ubiquitously. (In additional to the places I listed above where I've found bits of the truth I should add: the Hermetics and the Kabala and quantum mechanics.) Could it be said that every now and then an additional bit is reticulated? So-to-speak revealed? So 2-3-74 could contain one or more elements of the truth that are new? In one area the Evangelical Christians are correct: in regard to Bible prophecy. The Bible does contain archetypes that print out over and over again, and are --some of them -- applicable to present-day times (I need only recall Acts and the dream material in TEARS, the latter specifically being either from Daniel or Revelation). So one great realization is: the map is exploded; the map is splintered. (And, perhaps, the map is not complete; see Hussey on the map paradox, the vicious regression.) There is also a great deal of truth in Medieval realism, Which has influenced my thinking, my worldview, enormously. In 3-74 it seemed to me I'd reverted specifically to that. {folder 01 - 086} 10-24-80 6 If the eide are exploded through the spatiotemporal realm, so must be Nous: disintegrated here in realm #4; but if the percipient ascends from realm #4 he may see Nous re-collected, reintegrated and hence unitary, as it actually is (what I am saying is that the eide are not actually exploded; they are exploded in terms of the spatiotemporal realm, if my meaning is clear; since realm #4 is illusory, the explosion, the splintering, is illusory. And if this is true of the eide, the Forms, this also is true of Nous: our false categories of ordering, of arranging, time and space, explode and splinter the eide; and they explode and splinter Nous; but this is not really the case. This is why it is correct to say that our realm #4 and its spatiotemporal ordering are irreal. If they were real, then the eide and Nous would in actuality be exploded and splintered; but they are not. To see Nous integrated is not for Nous to reintegrate, but to be seen as it is and always is. This was what I saw that I called Valis: Nous reintegrated in terms of my perception of it: re-collected. Nous exploded (here in realm #4) is Nous banalized, as in the chapter headings in UBIK; Nous re-collected is as Ubik appears in the heading of the final chapter, no longer banalized, trivialized, debased into rubbish. This banalization is a measure of the Fall of this realm; and again it illustrates what I have remarked on: that things do not appear in this realm #4 as what they really are, that finally Christ will bring about what I call \"the great reversal,\" whereupon we will no longer see Nous (God) banalized and exploded, but, as if reversed, sacred and a unity: as it really is. Meanwhile, here, with things appearing in reverse to what their essence is, Nous is obscured; veiled. 10-25-80 But whereas a given eidos is finite in realm #4 --it only enters at certain places and certain times; i.e. is printed out at one place and time but not another-- Nous is ubiquitious. Therefore if it chooses to so-to-speak drop its mask and reverse appearances in realm #4 (enantiodromia) it is in everything at every time; it is infinite (cf Xenophanes). Or, put another way, it can be anything or any constellation of things and their processes at any place and any time. It is not quenched, quelled or subdued by realm #4, unless it (Nous) refrains from asserting itself deliberately. (But this would seem to point to it deliberately refraining from manifesting itself to us; this {folder 01 - 087} 10-25-80 Orphism. It's as if the \"second birth\" or \"birth in the spirit\" is in fact spiritual or even physical death run backward --retrograde-- in time. Eliade speaks of this as a sacred rite, as alchemy. 10-26-80 I was gazing at Harvey tonight and I was granted a vision: of him as all the cats who had come before (as Schopenhauer says); but I did not think it; I saw it in the same way that one sees motion in a movie. I saw the point of this whold morphologically arranged world and its relation to our spatiotemporal world; wherever in space a cat is and whenever in time, it is a perfect cat; there is no deterioration in --so-to-speak-- the information comprising CAT. Over millions of years that \"signal\" has not deteriorated or weakened or been contaminated; the cat now is a clear-cut and perfect a cat as the first cat; and what I saw sitting there was essentially an eternal cat, a cat outside of time and space, a cat replaced over and over again --exactly as Schopenhauer says--and still with us here and now as it was there and then, every cat I have ever seen and every cat that has ever been or will be; because the process has not ended. This was not a theory or an intellectual realization; I actually saw him as the eidos cat, instanted (or whatever the fucking word is; an instance of) the cat. I therefore saw this spatiotemporal world joined to the morphologically-arranged world of the eide through and in this cat, the two realms synchronized and superimposed, the instance and the eidos as one; Harvey was simultaneously an instance in the spatiotemporal realm of cat, and also the eidos cat. This is why my view (based on revelation) that the flux world feeds into the Form world (world of the phylogons) as reticulation and arborizing is not only more correct than Plato's but more logical and valuable; it is a sort of double emanation from higher to lower, from lower to higher (realms), as Plotinus says. what the individual cats do and are is not lost, although the individual cat is an epiphenomenon and fades out; but as it fades --not after it is gone but as it fades--there fades in another \"picture\" of cat, so that cat is unchanged as cat; cat is constant. So everything that I have figured out in the last two weeks came together tonight in this vision of my cat who is an eternal cat, just as I am an eternal person; it is all eternal and I saw it with my own eyes, how the superimposition works. {folder 01 - 088} 10-25-80 1 suggests Brahman. Could it not abolish realm #4 any time it (Nous) wished? Then it has let us fall; and it has the power to award us a theophany based on its theodicy --or on any principle it wishes: \"As it wills.\" Then it lets us suffer the consequences of our epistemological error. But perhaps it provides us with clues. Here is a theory I am fond of: it observes how we behave in a state of amnesia wherein we do now know who we are or what behavior will be rewarded, so we are ignorant of guile in culling rewards: we do not even know if it (Nous). On the other hand, a more Greek view would be that it intervenes to balance extremes; this is pure enantiodromia and fits Plato as well as Heraclitus. And is also Taoist. I.e. it is a self-regulating totally homeostatic entity maintaining internal harmonie. It seems to me that the key is: internal balance, and the mechanism for this is enantiodromia. And this accounts for (3-74). The \"Torah\" that relates to me speaks of troubles. Well, then a point of such extreme distress comes that due to fundamental principles of harmonie (balance) within the total system enantiodromia occurs as an alchemical transmutation of the situation: a conversion into its opposite. Surely this involves the regular oscillations in time by the dialectic (palintropos harmonie). There is some kind of \"emptyingfullness\" logic as described in the TAO TE CHING. It is",
  "raw_text_char_count": 11376,
  "works_referenced": [
    "Ubik",
    "VALIS"
  ],
  "linked_terms": [
    {
      "term_id": "TERM_2-3-74",
      "name": "2-3-74",
      "slug": "2-3-74",
      "match_type": "exact_mention",
      "confidence": 1,
      "matched_text": "2-3-74"
    },
    {
      "term_id": "TERM_acts",
      "name": "Acts",
      "slug": "acts",
      "match_type": "exact_mention",
      "confidence": 1,
      "matched_text": "Acts"
    },
    {
      "term_id": "TERM_actually",
      "name": "Actually",
      "slug": "actually",
      "match_type": "exact_mention",
      "confidence": 1,
      "matched_text": "actually"
    },
    {
      "term_id": "TERM_after",
      "name": "After",
      "slug": "after",
      "match_type": "exact_mention",
      "confidence": 1,
      "matched_text": "after"
    },
    {
      "term_id": "TERM_again",
      "name": "Again",
      "slug": "again",
      "match_type": "exact_mention",
      "confidence": 1,
      "matched_text": "again"
    },
    {
      "term_id": "TERM_although",
      "name": "Although",
      "slug": "although",
      "match_type": "exact_mention",
      "confidence": 1,
      "matched_text": "although"
    },
    {
      "term_id": "TERM_always",
      "name": "Always",
      "slug": "always",
      "match_type": "exact_mention",
      "confidence": 1,
      "matched_text": "always"
    },
    {
      "term_id": "TERM_another",
      "name": "Another",
      "slug": "another",
      "match_type": "exact_mention",
      "confidence": 1,
      "matched_text": "another"
    },
    {
      "term_id": "TERM_answer",
      "name": "Answer",
      "slug": "answer",
      "match_type": "exact_mention",
      "confidence": 1,
      "matched_text": "answer"
    },
    {
      "term_id": "TERM_anything",
      "name": "Anything",
      "slug": "anything",
      "match_type": "exact_mention",
      "confidence": 1,
      "matched_text": "anything"
    },
    {
      "term_id": "TERM_based",
      "name": "Based",
      "slug": "based",
      "match_type": "exact_mention",
      "confidence": 1,
      "matched_text": "based"
    },
    {
      "term_id": "TERM_because",
      "name": "Because",
      "slug": "because",
      "match_type": "exact_mention",
      "confidence": 1,
      "matched_text": "because"
    },
    {
      "term_id": "TERM_before",
      "name": "Before",
      "slug": "before",
      "match_type": "exact_mention",
      "confidence": 1,
      "matched_text": "before"
    },
    {
      "term_id": "TERM_being",
      "name": "Being",
      "slug": "being",
      "match_type": "exact_mention",
      "confidence": 1,
      "matched_text": "being"
    },
    {
      "term_id": "TERM_between",
      "name": "Between",
      "slug": "between",
      "match_type": "exact_mention",
      "confidence": 1,
      "matched_text": "between"
    },
    {
      "term_id": "TERM_bible",
      "name": "Bible",
      "slug": "bible",
      "match_type": "exact_mention",
      "confidence": 1,
      "matched_text": "Bible"
    },
    {
      "term_id": "TERM_birth",
      "name": "Birth",
      "slug": "birth",
      "match_type": "exact_mention",
      "confidence": 1,
      "matched_text": "birth"
    },
    {
      "term_id": "TERM_brahman",
      "name": "Brahman",
      "slug": "brahman",
      "match_type": "exact_mention",
      "confidence": 1,
      "matched_text": "Brahman"
    },
    {
      "term_id": "TERM_brahmanism",
      "name": "Brahmanism",
      "slug": "brahmanism",
      "match_type": "exact_mention",
      "confidence": 1,
      "matched_text": "Brahmanism"
    },
    {
      "term_id": "TERM_buddhism",
      "name": "Buddhism",
      "slug": "buddhism",
      "match_type": "exact_mention",
      "confidence": 1,
      "matched_text": "Buddhism"
    },
    {
      "term_id": "TERM_ching",
      "name": "Ching",
      "slug": "ching",
      "match_type": "exact_mention",
      "confidence": 1,
      "matched_text": "CHING"
    },
    {
      "term_id": "TERM_christ",
      "name": "Christ",
      "slug": "christ",
      "match_type": "exact_mention",
      "confidence": 1,
      "matched_text": "Christ"
    },
    {
      "term_id": "TERM_christian",
      "name": "Christian",
      "slug": "christian",
      "match_type": "exact_mention",
      "confidence": 1,
      "matched_text": "Christian"
    },
    {
      "term_id": "TERM_christianity",
      "name": "Christianity",
      "slug": "christianity",
      "match_type": "exact_mention",
      "confidence": 1,
      "matched_text": "Christianity"
    },
    {
      "term_id": "TERM_complete",
      "name": "Complete",
      "slug": "complete",
      "match_type": "exact_mention",
      "confidence": 1,
      "matched_text": "complete"
    },
    {
      "term_id": "TERM_could",
      "name": "Could",
      "slug": "could",
      "match_type": "exact_mention",
      "confidence": 1,
      "matched_text": "could"
    },
    {
      "term_id": "TERM_daniel",
      "name": "Daniel",
      "slug": "daniel",
      "match_type": "exact_mention",
      "confidence": 1,
      "matched_text": "Daniel"
    },
    {
      "term_id": "TERM_death",
      "name": "Death",
      "slug": "death",
      "match_type": "exact_mention",
      "confidence": 1,
      "matched_text": "death"
    },
    {
      "term_id": "TERM_dialectic",
      "name": "Dialectic",
      "slug": "dialectic",
      "match_type": "exact_mention",
      "confidence": 1,
      "matched_text": "dialectic"
    },
    {
      "term_id": "TERM_does",
      "name": "Does",
      "slug": "does",
      "match_type": "exact_mention",
      "confidence": 1,
      "matched_text": "does"
    },
    {
      "term_id": "TERM_dokos",
      "name": "Dokos",
      "slug": "dokos",
      "match_type": "exact_mention",
      "confidence": 1,
      "matched_text": "dokos"
    },
    {
      "term_id": "TERM_dream",
      "name": "Dream",
      "slug": "dream",
      "match_type": "exact_mention",
      "confidence": 1,
      "matched_text": "dream"
    },
    {
      "term_id": "TERM_eidos",
      "name": "Eidos",
      "slug": "eidos",
      "match_type": "exact_mention",
      "confidence": 1,
      "matched_text": "eidos"
    },
    {
      "term_id": "TERM_either",
      "name": "Either",
      "slug": "either",
      "match_type": "exact_mention",
      "confidence": 1,
      "matched_text": "either"
    },
    {
      "term_id": "TERM_eliade",
      "name": "Eliade",
      "slug": "eliade",
      "match_type": "exact_mention",
      "confidence": 1,
      "matched_text": "Eliade"
    },
    {
      "term_id": "TERM_emanation",
      "name": "Emanation",
      "slug": "emanation",
      "match_type": "exact_mention",
      "confidence": 1,
      "matched_text": "emanation"
    },
    {
      "term_id": "TERM_even",
      "name": "Even",
      "slug": "even",
      "match_type": "exact_mention",
      "confidence": 1,
      "matched_text": "even"
    },
    {
      "term_id": "TERM_everything",
      "name": "Everything",
      "slug": "everything",
      "match_type": "exact_mention",
      "confidence": 1,
      "matched_text": "everything"
    },
    {
      "term_id": "TERM_evil",
      "name": "Evil",
      "slug": "evil",
      "match_type": "exact_mention",
      "confidence": 1,
      "matched_text": "Evil"
    },
    {
      "term_id": "TERM_exactly",
      "name": "Exactly",
      "slug": "exactly",
      "match_type": "exact_mention",
      "confidence": 1,
      "matched_text": "exactly"
    },
    {
      "term_id": "TERM_fall",
      "name": "Fall",
      "slug": "fall",
      "match_type": "exact_mention",
      "confidence": 1,
      "matched_text": "Fall"
    },
    {
      "term_id": "TERM_final",
      "name": "Final",
      "slug": "final",
      "match_type": "exact_mention",
      "confidence": 1,
      "matched_text": "final"
    },
    {
      "term_id": "TERM_finally",
      "name": "Finally",
      "slug": "finally",
      "match_type": "exact_mention",
      "confidence": 1,
      "matched_text": "finally"
    },
    {
      "term_id": "TERM_fish",
      "name": "Fish",
      "slug": "fish",
      "match_type": "exact_mention",
      "confidence": 1,
      "matched_text": "fish"
    },
    {
      "term_id": "TERM_flux",
      "name": "Flux",
      "slug": "flux",
      "match_type": "exact_mention",
      "confidence": 1,
      "matched_text": "flux"
    },
    {
      "term_id": "TERM_folder",
      "name": "Folder",
      "slug": "folder",
      "match_type": "exact_mention",
      "confidence": 1,
      "matched_text": "folder"
    },
    {
      "term_id": "TERM_form",
      "name": "Form",
      "slug": "form",
      "match_type": "exact_mention",
      "confidence": 1,
      "matched_text": "Form"
    },
    {
      "term_id": "TERM_form-world",
      "name": "Form World",
      "slug": "form-world",
      "match_type": "exact_mention",
      "confidence": 1,
      "matched_text": "Form world"
    },
    {
      "term_id": "TERM_given",
      "name": "Given",
      "slug": "given",
      "match_type": "exact_mention",
      "confidence": 1,
      "matched_text": "given"
    },
    {
      "term_id": "TERM_gnosticism",
      "name": "Gnosticism",
      "slug": "gnosticism",
      "match_type": "exact_mention",
      "confidence": 1,
      "matched_text": "Gnosticism"
    },
    {
      "term_id": "TERM_good",
      "name": "Good",
      "slug": "good",
      "match_type": "exact_mention",
      "confidence": 1,
      "matched_text": "good"
    },
    {
      "term_id": "TERM_great",
      "name": "Great",
      "slug": "great",
      "match_type": "exact_mention",
      "confidence": 1,
      "matched_text": "great"
    },
    {
      "term_id": "TERM_greece",
      "name": "Greece",
      "slug": "greece",
      "match_type": "exact_mention",
      "confidence": 1,
      "matched_text": "Greece"
    },
    {
      "term_id": "TERM_greek",
      "name": "Greek",
      "slug": "greek",
      "match_type": "exact_mention",
      "confidence": 1,
      "matched_text": "Greek"
    },
    {
      "term_id": "TERM_have",
      "name": "Have",
      "slug": "have",
      "match_type": "exact_mention",
      "confidence": 1,
      "matched_text": "have"
    },
    {
      "term_id": "TERM_heraclitus",
      "name": "Heraclitus",
      "slug": "heraclitus",
      "match_type": "exact_mention",
      "confidence": 1,
      "matched_text": "Heraclitus"
    },
    {
      "term_id": "TERM_however",
      "name": "However",
      "slug": "however",
      "match_type": "exact_mention",
      "confidence": 1,
      "matched_text": "however"
    },
    {
      "term_id": "TERM_hussey",
      "name": "Hussey",
      "slug": "hussey",
      "match_type": "exact_mention",
      "confidence": 1,
      "matched_text": "Hussey"
    },
    {
      "term_id": "TERM_india",
      "name": "India",
      "slug": "india",
      "match_type": "exact_mention",
      "confidence": 1,
      "matched_text": "India"
    },
    {
      "term_id": "TERM_indian",
      "name": "Indian",
      "slug": "indian",
      "match_type": "exact_mention",
      "confidence": 1,
      "matched_text": "Indian"
    },
    {
      "term_id": "TERM_information",
      "name": "Information",
      "slug": "information",
      "match_type": "exact_mention",
      "confidence": 1,
      "matched_text": "information"
    },
    {
      "term_id": "TERM_into",
      "name": "Into",
      "slug": "into",
      "match_type": "exact_mention",
      "confidence": 1,
      "matched_text": "into"
    },
    {
      "term_id": "TERM_judaism",
      "name": "Judaism",
      "slug": "judaism",
      "match_type": "exact_mention",
      "confidence": 1,
      "matched_text": "Judaism"
    },
    {
      "term_id": "TERM_judo",
      "name": "Judo",
      "slug": "judo",
      "match_type": "exact_mention",
      "confidence": 1,
      "matched_text": "Judo"
    },
    {
      "term_id": "TERM_just",
      "name": "Just",
      "slug": "just",
      "match_type": "exact_mention",
      "confidence": 1,
      "matched_text": "just"
    },
    {
      "term_id": "TERM_kant",
      "name": "Kant",
      "slug": "kant",
      "match_type": "exact_mention",
      "confidence": 1,
      "matched_text": "Kant"
    },
    {
      "term_id": "TERM_like",
      "name": "Like",
      "slug": "like",
      "match_type": "exact_mention",
      "confidence": 1,
      "matched_text": "like"
    },
    {
      "term_id": "TERM_look",
      "name": "Look",
      "slug": "look",
      "match_type": "exact_mention",
      "confidence": 1,
      "matched_text": "Look"
    },
    {
      "term_id": "TERM_lower",
      "name": "Lower",
      "slug": "lower",
      "match_type": "exact_mention",
      "confidence": 1,
      "matched_text": "lower"
    },
    {
      "term_id": "TERM_mani",
      "name": "Mani",
      "slug": "mani",
      "match_type": "exact_mention",
      "confidence": 1,
      "matched_text": "Mani"
    },
    {
      "term_id": "TERM_many",
      "name": "Many",
      "slug": "many",
      "match_type": "exact_mention",
      "confidence": 1,
      "matched_text": "many"
    },
    {
      "term_id": "TERM_maya",
      "name": "Maya",
      "slug": "maya",
      "match_type": "exact_mention",
      "confidence": 1,
      "matched_text": "maya"
    },
    {
      "term_id": "TERM_maze",
      "name": "Maze",
      "slug": "maze",
      "match_type": "exact_mention",
      "confidence": 1,
      "matched_text": "maze"
    },
    {
      "term_id": "TERM_meanwhile",
      "name": "Meanwhile",
      "slug": "meanwhile",
      "match_type": "exact_mention",
      "confidence": 1,
      "matched_text": "Meanwhile"
    },
    {
      "term_id": "TERM_medieval",
      "name": "Medieval",
      "slug": "medieval",
      "match_type": "exact_mention",
      "confidence": 1,
      "matched_text": "Medieval"
    },
    {
      "term_id": "TERM_meta",
      "name": "Meta",
      "slug": "meta",
      "match_type": "exact_mention",
      "confidence": 1,
      "matched_text": "meta"
    },
    {
      "term_id": "TERM_more",
      "name": "More",
      "slug": "more",
      "match_type": "exact_mention",
      "confidence": 1,
      "matched_text": "more"
    },
    {
      "term_id": "TERM_mystery",
      "name": "Mystery",
      "slug": "mystery",
      "match_type": "exact_mention",
      "confidence": 1,
      "matched_text": "mystery"
    },
    {
      "term_id": "TERM_none",
      "name": "None",
      "slug": "none",
      "match_type": "exact_mention",
      "confidence": 1,
      "matched_text": "none"
    },
    {
      "term_id": "TERM_nous",
      "name": "Nous",
      "slug": "nous",
      "match_type": "exact_mention",
      "confidence": 1,
      "matched_text": "Nous"
    },
    {
      "term_id": "TERM_only",
      "name": "Only",
      "slug": "only",
      "match_type": "exact_mention",
      "confidence": 1,
      "matched_text": "only"
    },
    {
      "term_id": "TERM_orphism",
      "name": "Orphism",
      "slug": "orphism",
      "match_type": "exact_mention",
      "confidence": 1,
      "matched_text": "Orphism"
    },
    {
      "term_id": "TERM_other",
      "name": "Other",
      "slug": "other",
      "match_type": "exact_mention",
      "confidence": 1,
      "matched_text": "other"
    },
    {
      "term_id": "TERM_outside",
      "name": "Outside",
      "slug": "outside",
      "match_type": "exact_mention",
      "confidence": 1,
      "matched_text": "outside"
    },
    {
      "term_id": "TERM_parmenides",
      "name": "Parmenides",
      "slug": "parmenides",
      "match_type": "exact_mention",
      "confidence": 1,
      "matched_text": "Parmenides"
    },
    {
      "term_id": "TERM_part",
      "name": "Part",
      "slug": "part",
      "match_type": "exact_mention",
      "confidence": 1,
      "matched_text": "part"
    },
    {
      "term_id": "TERM_perception",
      "name": "Perception",
      "slug": "perception",
      "match_type": "exact_mention",
      "confidence": 1,
      "matched_text": "perception"
    },
    {
      "term_id": "TERM_perhaps",
      "name": "Perhaps",
      "slug": "perhaps",
      "match_type": "exact_mention",
      "confidence": 1,
      "matched_text": "perhaps"
    },
    {
      "term_id": "TERM_person",
      "name": "Person",
      "slug": "person",
      "match_type": "exact_mention",
      "confidence": 1,
      "matched_text": "person"
    },
    {
      "term_id": "TERM_physical",
      "name": "Physical",
      "slug": "physical",
      "match_type": "exact_mention",
      "confidence": 1,
      "matched_text": "physical"
    },
    {
      "term_id": "TERM_plato",
      "name": "Plato",
      "slug": "plato",
      "match_type": "exact_mention",
      "confidence": 1,
      "matched_text": "Plato"
    },
    {
      "term_id": "TERM_platonism",
      "name": "Platonism",
      "slug": "platonism",
      "match_type": "exact_mention",
      "confidence": 1,
      "matched_text": "Platonism"
    },
    {
      "term_id": "TERM_plotinus",
      "name": "Plotinus",
      "slug": "plotinus",
      "match_type": "exact_mention",
      "confidence": 1,
      "matched_text": "Plotinus"
    },
    {
      "term_id": "TERM_point",
      "name": "Point",
      "slug": "point",
      "match_type": "exact_mention",
      "confidence": 1,
      "matched_text": "point"
    },
    {
      "term_id": "TERM_power",
      "name": "Power",
      "slug": "power",
      "match_type": "exact_mention",
      "confidence": 1,
      "matched_text": "power"
    },
    {
      "term_id": "TERM_present",
      "name": "Present",
      "slug": "present",
      "match_type": "exact_mention",
      "confidence": 1,
      "matched_text": "present"
    },
    {
      "term_id": "TERM_probably",
      "name": "Probably",
      "slug": "probably",
      "match_type": "exact_mention",
      "confidence": 1,
      "matched_text": "Probably"
    },
    {
      "term_id": "TERM_pythagoras",
      "name": "Pythagoras",
      "slug": "pythagoras",
      "match_type": "exact_mention",
      "confidence": 1,
      "matched_text": "Pythagoras"
    },
    {
      "term_id": "TERM_real",
      "name": "Real",
      "slug": "real",
      "match_type": "exact_mention",
      "confidence": 1,
      "matched_text": "real"
    },
    {
      "term_id": "TERM_reality",
      "name": "Reality",
      "slug": "reality",
      "match_type": "exact_mention",
      "confidence": 1,
      "matched_text": "reality"
    },
    {
      "term_id": "TERM_really",
      "name": "Really",
      "slug": "really",
      "match_type": "exact_mention",
      "confidence": 1,
      "matched_text": "really"
    },
    {
      "term_id": "TERM_realm",
      "name": "Realm",
      "slug": "realm",
      "match_type": "exact_mention",
      "confidence": 1,
      "matched_text": "realm"
    },
    {
      "term_id": "TERM_reason",
      "name": "Reason",
      "slug": "reason",
      "match_type": "exact_mention",
      "confidence": 1,
      "matched_text": "reason"
    },
    {
      "term_id": "TERM_remember",
      "name": "Remember",
      "slug": "remember",
      "match_type": "exact_mention",
      "confidence": 1,
      "matched_text": "remember"
    },
    {
      "term_id": "TERM_revelation",
      "name": "Revelation",
      "slug": "revelation",
      "match_type": "exact_mention",
      "confidence": 1,
      "matched_text": "Revelation"
    },
    {
      "term_id": "TERM_sacred",
      "name": "Sacred",
      "slug": "sacred",
      "match_type": "exact_mention",
      "confidence": 1,
      "matched_text": "sacred"
    },
    {
      "term_id": "TERM_satan",
      "name": "Satan",
      "slug": "satan",
      "match_type": "exact_mention",
      "confidence": 1,
      "matched_text": "Satan"
    },
    {
      "term_id": "TERM_schopenhauer",
      "name": "Schopenhauer",
      "slug": "schopenhauer",
      "match_type": "exact_mention",
      "confidence": 1,
      "matched_text": "Schopenhauer"
    },
    {
      "term_id": "TERM_seen",
      "name": "Seen",
      "slug": "seen",
      "match_type": "exact_mention",
      "confidence": 1,
      "matched_text": "seen"
    },
    {
      "term_id": "TERM_self",
      "name": "Self",
      "slug": "self",
      "match_type": "exact_mention",
      "confidence": 1,
      "matched_text": "Self"
    },
    {
      "term_id": "TERM_sign",
      "name": "Sign",
      "slug": "sign",
      "match_type": "exact_mention",
      "confidence": 1,
      "matched_text": "sign"
    },
    {
      "term_id": "TERM_since",
      "name": "Since",
      "slug": "since",
      "match_type": "exact_mention",
      "confidence": 1,
      "matched_text": "Since"
    },
    {
      "term_id": "TERM_something",
      "name": "Something",
      "slug": "something",
      "match_type": "exact_mention",
      "confidence": 1,
      "matched_text": "something"
    },
    {
      "term_id": "TERM_soul",
      "name": "Soul",
      "slug": "soul",
      "match_type": "exact_mention",
      "confidence": 1,
      "matched_text": "Soul"
    },
    {
      "term_id": "TERM_space",
      "name": "Space",
      "slug": "space",
      "match_type": "exact_mention",
      "confidence": 1,
      "matched_text": "space"
    },
    {
      "term_id": "TERM_specifically",
      "name": "Specifically",
      "slug": "specifically",
      "match_type": "exact_mention",
      "confidence": 1,
      "matched_text": "specifically"
    },
    {
      "term_id": "TERM_spinoza",
      "name": "Spinoza",
      "slug": "spinoza",
      "match_type": "exact_mention",
      "confidence": 1,
      "matched_text": "Spinoza"
    },
    {
      "term_id": "TERM_spirit",
      "name": "Spirit",
      "slug": "spirit",
      "match_type": "exact_mention",
      "confidence": 1,
      "matched_text": "spirit"
    },
    {
      "term_id": "TERM_still",
      "name": "Still",
      "slug": "still",
      "match_type": "exact_mention",
      "confidence": 1,
      "matched_text": "still"
    },
    {
      "term_id": "TERM_such",
      "name": "Such",
      "slug": "such",
      "match_type": "exact_mention",
      "confidence": 1,
      "matched_text": "Such"
    },
    {
      "term_id": "TERM_surely",
      "name": "Surely",
      "slug": "surely",
      "match_type": "exact_mention",
      "confidence": 1,
      "matched_text": "Surely"
    },
    {
      "term_id": "TERM_take",
      "name": "Take",
      "slug": "take",
      "match_type": "exact_mention",
      "confidence": 1,
      "matched_text": "take"
    },
    {
      "term_id": "TERM_taoism",
      "name": "Taoism",
      "slug": "taoism",
      "match_type": "exact_mention",
      "confidence": 1,
      "matched_text": "Taoism"
    },
    {
      "term_id": "TERM_taoist",
      "name": "Taoist",
      "slug": "taoist",
      "match_type": "exact_mention",
      "confidence": 1,
      "matched_text": "Taoist"
    },
    {
      "term_id": "TERM_tears",
      "name": "Tears",
      "slug": "tears",
      "match_type": "exact_mention",
      "confidence": 1,
      "matched_text": "TEARS"
    },
    {
      "term_id": "TERM_their",
      "name": "Their",
      "slug": "their",
      "match_type": "exact_mention",
      "confidence": 1,
      "matched_text": "their"
    },
    {
      "term_id": "TERM_theophany",
      "name": "Theophany",
      "slug": "theophany",
      "match_type": "exact_mention",
      "confidence": 1,
      "matched_text": "theophany"
    },
    {
      "term_id": "TERM_therefore",
      "name": "Therefore",
      "slug": "therefore",
      "match_type": "exact_mention",
      "confidence": 1,
      "matched_text": "Therefore"
    },
    {
      "term_id": "TERM_things",
      "name": "Things",
      "slug": "things",
      "match_type": "exact_mention",
      "confidence": 1,
      "matched_text": "things"
    },
    {
      "term_id": "TERM_think",
      "name": "Think",
      "slug": "think",
      "match_type": "exact_mention",
      "confidence": 1,
      "matched_text": "think"
    },
    {
      "term_id": "TERM_thinking",
      "name": "Thinking",
      "slug": "thinking",
      "match_type": "exact_mention",
      "confidence": 1,
      "matched_text": "thinking"
    },
    {
      "term_id": "TERM_thought",
      "name": "Thought",
      "slug": "thought",
      "match_type": "exact_mention",
      "confidence": 1,
      "matched_text": "thought"
    },
    {
      "term_id": "TERM_through",
      "name": "Through",
      "slug": "through",
      "match_type": "exact_mention",
      "confidence": 1,
      "matched_text": "through"
    },
    {
      "term_id": "TERM_time",
      "name": "Time",
      "slug": "time",
      "match_type": "exact_mention",
      "confidence": 1,
      "matched_text": "time"
    },
    {
      "term_id": "TERM_torah",
      "name": "Torah",
      "slug": "torah",
      "match_type": "exact_mention",
      "confidence": 1,
      "matched_text": "Torah"
    },
    {
      "term_id": "TERM_total",
      "name": "Total",
      "slug": "total",
      "match_type": "exact_mention",
      "confidence": 1,
      "matched_text": "total"
    },
    {
      "term_id": "TERM_true",
      "name": "True",
      "slug": "true",
      "match_type": "exact_mention",
      "confidence": 1,
      "matched_text": "true"
    },
    {
      "term_id": "TERM_truth",
      "name": "Truth",
      "slug": "truth",
      "match_type": "exact_mention",
      "confidence": 1,
      "matched_text": "truth"
    },
    {
      "term_id": "TERM_ubik",
      "name": "Ubik",
      "slug": "ubik",
      "match_type": "exact_mention",
      "confidence": 1,
      "matched_text": "UBIK"
    },
    {
      "term_id": "TERM_unless",
      "name": "Unless",
      "slug": "unless",
      "match_type": "exact_mention",
      "confidence": 1,
      "matched_text": "unless"
    },
    {
      "term_id": "TERM_using",
      "name": "Using",
      "slug": "using",
      "match_type": "exact_mention",
      "confidence": 1,
      "matched_text": "using"
    },
    {
      "term_id": "TERM_valis",
      "name": "Valis",
      "slug": "valis",
      "match_type": "exact_mention",
      "confidence": 1,
      "matched_text": "Valis"
    },
    {
      "term_id": "TERM_very",
      "name": "Very",
      "slug": "very",
      "match_type": "exact_mention",
      "confidence": 1,
      "matched_text": "very"
    },
    {
      "term_id": "TERM_vision",
      "name": "Vision",
      "slug": "vision",
      "match_type": "exact_mention",
      "confidence": 1,
      "matched_text": "vision"
    },
    {
      "term_id": "TERM_well",
      "name": "Well",
      "slug": "well",
      "match_type": "exact_mention",
      "confidence": 1,
      "matched_text": "well"
    },
    {
      "term_id": "TERM_were",
      "name": "Were",
      "slug": "were",
      "match_type": "exact_mention",
      "confidence": 1,
      "matched_text": "were"
    },
    {
      "term_id": "TERM_whatever",
      "name": "Whatever",
      "slug": "whatever",
      "match_type": "exact_mention",
      "confidence": 1,
      "matched_text": "whatever"
    },
    {
      "term_id": "TERM_whereas",
      "name": "Whereas",
      "slug": "whereas",
      "match_type": "exact_mention",
      "confidence": 1,
      "matched_text": "whereas"
    },
    {
      "term_id": "TERM_will",
      "name": "Will",
      "slug": "will",
      "match_type": "exact_mention",
      "confidence": 1,
      "matched_text": "will"
    },
    {
      "term_id": "TERM_within",
      "name": "Within",
      "slug": "within",
      "match_type": "exact_mention",
      "confidence": 1,
      "matched_text": "within"
    },
    {
      "term_id": "TERM_word",
      "name": "Word",
      "slug": "word",
      "match_type": "exact_mention",
      "confidence": 1,
      "matched_text": "word"
    },
    {
      "term_id": "TERM_world",
      "name": "World",
      "slug": "world",
      "match_type": "exact_mention",
      "confidence": 1,
      "matched_text": "world"
    },
    {
      "term_id": "TERM_would",
      "name": "Would",
      "slug": "would",
      "match_type": "exact_mention",
      "confidence": 1,
      "matched_text": "would"
    },
    {
      "term_id": "TERM_xenophanes",
      "name": "Xenophanes",
      "slug": "xenophanes",
      "match_type": "exact_mention",
      "confidence": 1,
      "matched_text": "Xenophanes"
    },
    {
      "term_id": "TERM_years",
      "name": "Years",
      "slug": "years",
      "match_type": "exact_mention",
      "confidence": 1,
      "matched_text": "years"
    },
    {
      "term_id": "TERM_zoroastrianism",
      "name": "Zoroastrianism",
      "slug": "zoroastrianism",
      "match_type": "exact_mention",
      "confidence": 1,
      "matched_text": "Zoroastrianism"
    },
    {
      "term_id": "TERM_hermetic",
      "name": "Hermetic",
      "slug": "hermetic",
      "match_type": "alias_mention",
      "confidence": 2,
      "matched_text": "Hermetics"
    },
    {
      "term_id": "TERM_acts",
      "name": "Acts",
      "slug": "acts",
      "match_type": "conceptual",
      "confidence": 4,
      "matched_text": "Acts"
    },
    {
      "term_id": "TERM_bible",
      "name": "Bible",
      "slug": "bible",
      "match_type": "conceptual",
      "confidence": 4,
      "matched_text": "Bible"
    },
    {
      "term_id": "TERM_christ",
      "name": "Christ",
      "slug": "christ",
      "match_type": "conceptual",
      "confidence": 4,
      "matched_text": "Christ"
    },
    {
      "term_id": "TERM_heraclitus",
      "name": "Heraclitus",
      "slug": "heraclitus",
      "match_type": "conceptual",
      "confidence": 4,
      "matched_text": "Heraclitus"
    },
    {
      "term_id": "TERM_mani",
      "name": "Mani",
      "slug": "mani",
      "match_type": "conceptual",
      "confidence": 4,
      "matched_text": "Mani"
    },
    {
      "term_id": "TERM_parmenides",
      "name": "Parmenides",
      "slug": "parmenides",
      "match_type": "conceptual",
      "confidence": 4,
      "matched_text": "Parmenides"
    },
    {
      "term_id": "TERM_plato",
      "name": "Plato",
      "slug": "plato",
      "match_type": "conceptual",
      "confidence": 4,
      "matched_text": "Plato"
    },
    {
      "term_id": "TERM_plotinus",
      "name": "Plotinus",
      "slug": "plotinus",
      "match_type": "conceptual",
      "confidence": 4,
      "matched_text": "Plotinus"
    },
    {
      "term_id": "TERM_pythagoras",
      "name": "Pythagoras",
      "slug": "pythagoras",
      "match_type": "conceptual",
      "confidence": 4,
      "matched_text": "Pythagoras"
    },
    {
      "term_id": "TERM_revelation",
      "name": "Revelation",
      "slug": "revelation",
      "match_type": "conceptual",
      "confidence": 4,
      "matched_text": "Revelation"
    },
    {
      "term_id": "TERM_spinoza",
      "name": "Spinoza",
      "slug": "spinoza",
      "match_type": "conceptual",
      "confidence": 4,
      "matched_text": "Spinoza"
    },
    {
      "term_id": "TERM_tears",
      "name": "Tears",
      "slug": "tears",
      "match_type": "conceptual",
      "confidence": 4,
      "matched_text": "TEARS"
    },
    {
      "term_id": "TERM_torah",
      "name": "Torah",
      "slug": "torah",
      "match_type": "conceptual",
      "confidence": 4,
      "matched_text": "Torah"
    },
    {
      "term_id": "TERM_ubik",
      "name": "Ubik",
      "slug": "ubik",
      "match_type": "conceptual",
      "confidence": 4,
      "matched_text": "UBIK"
    },
    {
      "term_id": "TERM_valis",
      "name": "Valis",
      "slug": "valis",
      "match_type": "conceptual",
      "confidence": 4,
      "matched_text": "VALIS"
    },
    {
      "term_id": "TERM_xenophanes",
      "name": "Xenophanes",
      "slug": "xenophanes",
      "match_type": "conceptual",
      "confidence": 4,
      "matched_text": "Xenophanes"
    }
  ],
  "linked_names": [],
  "evidence_excerpts": [
    {
      "text": "{folder 01 - 084}\n\n10-24-80 4\n\nSo I am saying that Indian thought is wrong when it assigns to cause to maya; I say, with Zoroaster, \"There is a magician.\" This is Zoroastrianism --and Mani and Gnosticism-- blended with Indian thought about maya and karma. With Christ viewed as the one who wakes us, who causes us to remember. Then it is not accident that it was the Christian fish sign that caused me to remember, to cease to forget. That is what it is supposed to do ... counteract the Lie (the del",
      "matched_alias": "India",
      "term_id": "TERM_india",
      "term_name": "India",
      "term_slug": "india"
    },
    {
      "text": "{folder 01 - 084}\n\n10-24-80 4\n\nSo I am saying that Indian thought is wrong when it assigns to cause to maya; I say, with Zoroaster, \"There is a magician.\" This is Zoroastrianism --and Mani and Gnosticism-- blended with Indian thought about maya and karma. With Christ viewed as the one who wakes us, who causes us to remember. Then it is not accident that it was the Christian fish sign that caused me to remember, to cease to forget. That is what it is supposed to do ... counteract the Lie (the del",
      "matched_alias": "Indian",
      "term_id": "TERM_indian",
      "term_name": "Indian",
      "term_slug": "indian"
    },
    {
      "text": "{folder 01 - 084}\n\n10-24-80 4\n\nSo I am saying that Indian thought is wrong when it assigns to cause to maya; I say, with Zoroaster, \"There is a magician.\" This is Zoroastrianism --and Mani and Gnosticism-- blended with Indian thought about maya and karma. With Christ viewed as the one who wakes us, who causes us to remember. Then it is not accident that it was the Christian fish sign that caused me to remember, to cease to forget. That is what it is supposed to do ... counteract the Lie (the del",
      "matched_alias": "Judo",
      "term_id": "TERM_judo",
      "term_name": "Judo",
      "term_slug": "judo"
    },
    {
      "text": "{folder 01 - 085}\n\n10-24-80\n\nIn that case, each given system is in itself part of the enslaving snare of delusion; in other words, as soon as I avow one philosopher or system (e.g. Spinoza or Schopenhauer or Kant or Anaxagoras or Parmenides or Gnosticism) I have become again or more ensnared, as I am by this spatiotemporal world itself; it is as if the eidos of Truth is exploded and splintered like all the eide. And all the Selves and Souls. But what else could you expect here in realm #4? Since",
      "matched_alias": "Kant",
      "term_id": "TERM_kant",
      "term_name": "Kant",
      "term_slug": "kant"
    },
    {
      "text": "{folder 01 - 085}\n\n10-24-80\n\nIn that case, each given system is in itself part of the enslaving snare of delusion; in other words, as soon as I avow one philosopher or system (e.g. Spinoza or Schopenhauer or Kant or Anaxagoras or Parmenides or Gnosticism) I have become again or more ensnared, as I am by this spatiotemporal world itself; it is as if the eidos of Truth is exploded and splintered like all the eide. And all the Selves and Souls. But what else could you expect here in realm #4? Since",
      "matched_alias": "Schopenhauer",
      "term_id": "TERM_schopenhauer",
      "term_name": "Schopenhauer",
      "term_slug": "schopenhauer"
    },
    {
      "text": "Orphism. It's as if the \"second birth\" or \"birth in the spirit\" is in fact spiritual or even physical death run backward --retrograde-- in time. Eliade speaks of this as a sacred rite, as alchemy.\n\n10-26-80\n\nI was gazing at Harvey tonight and I was granted a vision: of him as all the cats who had come before (as Schopenhauer says); but I did not think it; I saw it in the same way that one sees motion in a movie. I saw the point of this whold morphologically arranged world and its relation to our",
      "matched_alias": "Schopenhauer",
      "term_id": "TERM_schopenhauer",
      "term_name": "Schopenhauer",
      "term_slug": "schopenhauer"
    }
  ],
  "neighbors": [
    {
      "seg_id": "SEG_EXEG_1978-10-10_SECTION_016_290",
      "title": "1978-10-10_SECTION_016_290.txt",
      "position": 290
    },
    {
      "seg_id": "SEG_EXEG_1978-10-10_SECTION_016_292",
      "title": "1978-10-10_SECTION_016_292.txt",
      "position": 292
    }
  ],
  "document": {
    "title": "Letter",
    "doc_type": "exegesis_section",
    "author": "Philip K. Dick",
    "date_display": "October 10, 1978"
  }
}