{
  "name_id": "NAME_luba-luft",
  "canonical_form": "Luba Luft",
  "slug": "luba-luft",
  "entity_type": "character",
  "source_type": "fiction",
  "status": "provisional",
  "review_state": "machine-drafted",
  "etymology": "Luft = German for air",
  "origin_language": null,
  "allusion_type": null,
  "allusion_target": null,
  "wordplay_note": "Luba = love; she sings of love while made of circuits",
  "symbolic_note": null,
  "card_description": "Luba Luft (meaning \"Luft = German for air\") is a character in Philip K. Dick's *Do Androids Dream of Electric Sheep?*. Android opera singer whose artistic passion makes Deckard question retiring her. Name note: Luba = love; she sings of love while made of circuits. Art and beauty as markers of the soul — can a machine create genuine art?. First appears in *Do Androids Dream of Electric Sheep?*.",
  "full_description": null,
  "mention_count": 0,
  "first_work": "Do Androids Dream of Electric Sheep?",
  "work_list": [
    "Do Androids Dream of Electric Sheep?"
  ],
  "reference_id": "REF_literary_luba-luft",
  "provenance": "ingest_fiction_characters",
  "notes": null,
  "created_at": "2026-03-14 06:43:21",
  "updated_at": "2026-03-14 06:49:52",
  "segment_mention_count": 0,
  "aliases": [],
  "linked_segments": [],
  "related_terms": [],
  "reference": {
    "canonical_form": "Luba Luft",
    "domain": "literary",
    "brief": "Android opera singer whose artistic passion makes Deckard question retiring her",
    "etymology": "Luft = German for air",
    "origin_language": null,
    "significance": "Art and beauty as markers of the soul — can a machine create genuine art?",
    "source_text": "Do Androids Dream of Electric Sheep?"
  }
}