{
  "doc_id": "DOC_ARCH_DAILY_INDEPENDENT_JOURNAL_1963_04_04_PAG",
  "title": "Daily Independent Journal — April 4, 1963 (Page 30)",
  "slug": "daily-independent-journal-1963-04-04-page-30",
  "author": "Daily Independent Journal",
  "doc_type": "archive_pdf",
  "category": "newspaper",
  "date_display": "1963",
  "date_start": "1963",
  "is_pkd_authored": false,
  "card_summary": "https://www.newspapers.com/image/81639422/ Daily Independent Journal (San Rafael, California) · Thu, Apr 4, 1963 · Page 30 Downloaded on Apr 5, 2025 Clipped By: pwshelton8296 Aug 12, 2024 Copyright...",
  "page_count": 1,
  "ingest_level": "metadata_only",
  "extraction_status": "complete",
  "evidentiary_lane": "E",
  "source_reliability": "primary_other",
  "page_summary": "https://www.newspapers.com/image/81639422/ Daily Independent Journal (San Rafael, California) · Thu, Apr 4, 1963 · Page 30 Downloaded on Apr 5, 2025 Clipped By: pwshelton8296 Aug 12, 2024 Copyright © 2025 Newspapers.com.",
  "assets": [
    {
      "path": "PaulPKDarchive/PKDpdf/Daily_Independent_Journal_1963_04_04_Page_30.pdf",
      "type": "pdf",
      "size_mb": null
    }
  ]
}