{
  "seg_id": "SEG_EXEG_1978-10-10_SECTION_016_256",
  "doc_id": "DOC_EXEG_SECTION_016",
  "slug": "1978-10-10-section-016-256",
  "title": "1978-10-10_SECTION_016_256.txt",
  "position": 256,
  "date_start": "1978-10-10",
  "date_end": "1978-10-10",
  "date_display": "October 10, 1978",
  "date_confidence": "exact",
  "date_basis": "chunk_manifest",
  "concise_summary": null,
  "key_claims": null,
  "recurring_concepts": null,
  "people_entities": null,
  "texts_works": null,
  "autobiographical": null,
  "theological_motifs": null,
  "literary_self_ref": null,
  "symbols_images": null,
  "tensions": null,
  "evidence_quotes": null,
  "uncertainty_flags": null,
  "reading_excerpt": null,
  "word_count": 2000,
  "raw_text": "that self-perception is essential to the Godhead for it to be (to possess esse), because its Sein is related in some way to its intelligere, to its knowing, since it is a mind. It could not really be until it understood itself, and in understanding itself it caused itself to enter a series of infinite regressions (permuta¬ tions, in a dialectic, its wisdom and its power divided). Selfawareness, is automatically a dynamic process, not a static one. The entire universe came into existence upon its turning its attention on its own nature (intelligere directed at esse). But for this to occur, it must be self aware, and this is what 3-74 was: an epiphany [Handwritten note on the left margin:] (Of course the original cultural purpose of the Eucharist was to \"cause\" this self-caused coming into existence of the Holy Spirit in you; it acted - like the Golden Fish sign - to remind you of the Last Supper - to promote anamnesis!) [Handwritten note on the bottom margin:] ( So the Golden Fish sign actually did for me became of the pentathol, what the Eucharist was supposed to do: cause anamnesis + bring in the Holy Spirit) -56- [Handwritten note on the top margin:] (The E.B. says yes, The Eucharist is supposed to produce ananmnesis of The Passion + death of Christ - + this is so - but what is missing is the realization that the ultimate purpose is to cause the Spirit of Christ -the Holy Spirit - to \"enter\" you; it occur in you, actually be Them, not just remembered.This knowledge is not lost.) of self-awareness.,.and yet in it the dialectic finally stops; first there is the dialectic (I understood that first) and then there is, finally, a stasis, which is to say a healing of the schism into that which perceives (intelligere) and that which is perceived (esse). A reconciliation has taken place, the mysterium coniunctionis The opposites in it are reconciled; it is no longer divided into the half which knows and the half which is known (wisdom and power respec¬ tively); it is back to its primordial state, having driven by means of the dialectic the permutations through infinity to their resolution which is where they began (so they are not infinite; a point comes when the metakosmos is complete; at that point the permutations stop; flux stops and time is abolished; and the Godhead is no longer riven). This is why my thoughts came faster and faster, why I rushed down that tunnel; why I saw the graphics; it was due to selfawareness set off by the golden fish sign. The conclusion of this was my seeing Valis as a unity, Parmenides' unchanging One. It would seem that the dialectic process will eventually be exhausted, although I don't know why logically; perhaps the permutations come faster and faster and there is an upper limit to how fast they can come...time gives out, the acceleration having reached a point beyond which time converts into space. So time isn't infinitely divisible, as is space. it seems to me, however, that there is another possi¬ bility? the Godhead can at a certain point know itself absolutely, that this flux process is not infinite simply because it is not infinite; a point arrives at which there is nothing else to know, and there it freezes. Flash-cutting turns into freeze frame. This is what happened with the phosphene graphics, for instance. [Handwritten note on the left margin:] (Remembering [Christ's] Passion + death would only produce a mood of sorrow; The Holly Spirit is risen Christ + would - does - promote Joy, not sorrow . The Imperial Church has now not only half of the sacrament - the really important second part that most matters - the true mirracle + purpose is missing!) [Handwritten note on the bottom margin:] (The Imperial Church has forgotten what it is supposed to remember; the message is not 'Christ's crucified' but Christ risen + with us again! ) -57- [Handwritten note on the top margin:] (So what originally was a sacrament of Joy has become a comemoration of suffering, sacrifice + death - defeating the whole purpose of the Lord's supper. Because the Spirit does not enter you, of course the sacrament is holy - but pointless.) This would correspond with the completion of the macrometasoma. There is such a point as this: its completion. So I am now saying that the construction of the macrometasoma is a representation of the Godhead knowing itself as it permutes down the time axis driven by the antithetical dialectic; it is the Godhead in process (as Whitehead and Bergson taught). But a point comes where this ends: the structure is finished. No more reticulation and arborizing is possible. If it were not so, how could one speak of the Mind completing itself? Perfecting itself? What would be the point of Wisdom playing Big Nigger with creative power? It would just go on forever with no resolution. After all, everything that occurs is added as an accretion to the macrometasoma- The Wise Mind —Hagia Sophia—- may reach a point where (this is a thought) that anamnesis ends the schism and hence the dialectic; my 3-74 experience is evidence that such a end, which is a return to the primordial pre-schismatic state, is beginning to be reached. The two sides of the dialectic are perceived as one internally consistent unity. The Wise Mind has remembered its identiy. (Had it forgotten? Is the dialectic due to its forgetting? And when it remembers, the dialectic ends, because the Wise Mind recognizes its opponent, the dark counter-player, as itself — as I depict in VALIS REGAINED? Is that why the flux ceases and pure structure is seen? Pure unity? Parmenides* unchanging One? Where motion is impossible? Then recognizing its opponent as itself is another way of saying, \"It has achieved self-awareness.\" This was its goal. And this is what happens in VALIS REGAINED. The Wise Mind had fallen below the threshold of awareness of its opponent as its own self, and this is self-alienation; this is the schism; this is a lack of selfawareness, which is what it is striving for. [Handwritten note on the left margin:] (+ them in 2-3-74 the actual thing [long forgotten?] did happen to me - the epiphany in me -[illegible] by Christ's spirit without my intending it) -58- [Handwritten note on the top margin:] ( I know what the precise necessary recollection - insight - that's missing is, because I had it when I saw the Golden Fish Sign: Christ Lives!) (i.e. is here with us now + then it comes to be[ing?] Christ in the form of Holy Spirit.) This self-awareness was expressed in my dream where the plaque made from my crimson shirt and white tie was held out to me by the cleaning woman, I grunted in recognition. This could well represent the Wise Mind (myself) seeing its opponent for what it is: a forgery. The opponent is not real (that is, not a real opponent). The game has been a delusion into which the Godhead itself fell. Then the Godhead itself fell prey to maya (Dedalus built the maze and then fell into it, as I put it in VALIS). The opponent is a forgery and there is no antithetical combat; it is a game and nothing but a game; it is irreal. However, this waking up by the Godhead was due to a sign it itself placed in the process to wake it up, to cause it to remember. It remembers that, too. So its wholeness is restored, its unity and integrity. What a moment for the Wise Mind, to identify to dark counter¬ player, its adversary, as its own self. This is the monism that Evelyn Underhill speaks so slightingly of, but it is Sankara’s tat tvam asi; this occurs for the Godhead itself. Perhaps in its effort to know itself it became progressively more alienated from itself, farther and farther from its goal as the dialectic drove/drives its two halves along — and then moments come when it recognizes itself again, although perhaps locally and temporarily, epicenters of restored unity. I just cannot get away from the Gnostic idea of a crisis in the Godhead in which the Godhead split in half or even into pieces; but the dialectic suggests in half, into two antithetical sides. Its effort to understand itself has led it into a series of changes the result of which is not greater self-knowledge but greater self-alienation. However, at the [Handwritten note on the left margin:] ( So the message + sacrament of the Imperial Church is not \"Christ risen (vicorious) + with us\" but \"Christ suffering + dead - taken from us\" - a message of defeat. Interesting the true message is 180° reversed, + as a result the [cotinue below] [Handwritten note on the bottom margin:] Imperial Church Celebrates + dwells in suffering, the stations of the Cross, etc,+ not joyous Feast of the Harvest.) There is something else very strange about the Holy Spirit besides it only existing (i.e. in you) if you believe in the risen Christ being here now (i.e. in it, the Spirit). Christ, in John, says: \"I still have many things to say to you but they would be too much for you now. But when the Spirit of truth comes he will lead you to the complete truth, since he will not be speaking as from himself but will say only what he has learnt; and he will tell you of the things to come.\" The Holy Spirit picks up where Christ has left off. As if completing a sequence of information. But (as I know from 3-74) he does not verbally convey this; he — shows you Christ and from the interior of Christ's mind, and shows you Christ externally...crudely, it's \"show, not tell,\" but how does he do this? You literally see Christ (what I called Valis) and you are in Christ qua mind. But (I seem to be saying) Christ in a sense is not there. This is something like the Eucharist, like transubstantiation, done by the Holy Spirit apparently on whatever's nearby (it doesn't have to be bread and wine; it can be half the room of your apartment and the objects and processes therein). But 1 think this becomes true only as/when the Spirit does it; so the Spirit doesn't just reveal what is really there; the Spirit causes it to happen; or there ceases to be an distinction between you perceiving it and it happening... so the question, \"Is it Christ if you can't see it?\" has no meaning. It's as if the Spirit re-creates Christ at the point where Christ left off with the disciples; I'm saying, You generate the Spirit in your mind by the mysterium coniunctionis, and then the Spirit generates Christ in the outer world — turns the world into what I call the macrometasoma or Valis, structure, -61- metakosmos, pattern, integrated unity of the unrelated plural. This is transubstantiation, not just like it. The Eucharist takes place, performed by the Spirit, and it's real; it's not just a re¬ enactment of the Lord's Supper...it has something to do with time, though. You’re back at the time —and the place— of Acts, where Christ was last seen by the disciples. There is continuity of Christ, here. It's as if the Spirit is a transparent mechanism that acts as a lens or intermediary state between you and Christ. The Spirit and the risen Christ can't be separated; wherever the Spirit is, there is Christ; contrarily, there is no Christ unless you have the Spirit in you. But then, What is Christ under these circumstances? Not a man. There is nothing there that wasn’t there before, except the linking. If the Spirit can turn anything into Christ —the weeds in the alley— what, then, is Christ? If this is not a revelation by the Spirit that the",
  "raw_text_char_count": 11345,
  "linked_terms": [
    {
      "term_id": "TERM_2-3-74",
      "name": "2-3-74",
      "slug": "2-3-74",
      "match_type": "exact_mention",
      "confidence": 1,
      "matched_text": "2-3-74"
    },
    {
      "term_id": "TERM_acts",
      "name": "Acts",
      "slug": "acts",
      "match_type": "exact_mention",
      "confidence": 1,
      "matched_text": "Acts"
    },
    {
      "term_id": "TERM_actually",
      "name": "Actually",
      "slug": "actually",
      "match_type": "exact_mention",
      "confidence": 1,
      "matched_text": "actually"
    },
    {
      "term_id": "TERM_after",
      "name": "After",
      "slug": "after",
      "match_type": "exact_mention",
      "confidence": 1,
      "matched_text": "After"
    },
    {
      "term_id": "TERM_again",
      "name": "Again",
      "slug": "again",
      "match_type": "exact_mention",
      "confidence": 1,
      "matched_text": "again"
    },
    {
      "term_id": "TERM_although",
      "name": "Although",
      "slug": "although",
      "match_type": "exact_mention",
      "confidence": 1,
      "matched_text": "although"
    },
    {
      "term_id": "TERM_anamnesis",
      "name": "Anamnesis",
      "slug": "anamnesis",
      "match_type": "exact_mention",
      "confidence": 1,
      "matched_text": "anamnesis"
    },
    {
      "term_id": "TERM_another",
      "name": "Another",
      "slug": "another",
      "match_type": "exact_mention",
      "confidence": 1,
      "matched_text": "another"
    },
    {
      "term_id": "TERM_anything",
      "name": "Anything",
      "slug": "anything",
      "match_type": "exact_mention",
      "confidence": 1,
      "matched_text": "anything"
    },
    {
      "term_id": "TERM_apparently",
      "name": "Apparently",
      "slug": "apparently",
      "match_type": "exact_mention",
      "confidence": 1,
      "matched_text": "apparently"
    },
    {
      "term_id": "TERM_back",
      "name": "Back",
      "slug": "back",
      "match_type": "exact_mention",
      "confidence": 1,
      "matched_text": "back"
    },
    {
      "term_id": "TERM_because",
      "name": "Because",
      "slug": "because",
      "match_type": "exact_mention",
      "confidence": 1,
      "matched_text": "because"
    },
    {
      "term_id": "TERM_before",
      "name": "Before",
      "slug": "before",
      "match_type": "exact_mention",
      "confidence": 1,
      "matched_text": "before"
    },
    {
      "term_id": "TERM_being",
      "name": "Being",
      "slug": "being",
      "match_type": "exact_mention",
      "confidence": 1,
      "matched_text": "being"
    },
    {
      "term_id": "TERM_between",
      "name": "Between",
      "slug": "between",
      "match_type": "exact_mention",
      "confidence": 1,
      "matched_text": "between"
    },
    {
      "term_id": "TERM_beyond",
      "name": "Beyond",
      "slug": "beyond",
      "match_type": "exact_mention",
      "confidence": 1,
      "matched_text": "beyond"
    },
    {
      "term_id": "TERM_cause",
      "name": "Cause",
      "slug": "cause",
      "match_type": "exact_mention",
      "confidence": 1,
      "matched_text": "cause"
    },
    {
      "term_id": "TERM_christ",
      "name": "Christ",
      "slug": "christ",
      "match_type": "exact_mention",
      "confidence": 1,
      "matched_text": "Christ"
    },
    {
      "term_id": "TERM_church",
      "name": "Church",
      "slug": "church",
      "match_type": "exact_mention",
      "confidence": 1,
      "matched_text": "Church"
    },
    {
      "term_id": "TERM_coming",
      "name": "Coming",
      "slug": "coming",
      "match_type": "exact_mention",
      "confidence": 1,
      "matched_text": "coming"
    },
    {
      "term_id": "TERM_complete",
      "name": "Complete",
      "slug": "complete",
      "match_type": "exact_mention",
      "confidence": 1,
      "matched_text": "complete"
    },
    {
      "term_id": "TERM_conclusion",
      "name": "Conclusion",
      "slug": "conclusion",
      "match_type": "exact_mention",
      "confidence": 1,
      "matched_text": "conclusion"
    },
    {
      "term_id": "TERM_could",
      "name": "Could",
      "slug": "could",
      "match_type": "exact_mention",
      "confidence": 1,
      "matched_text": "could"
    },
    {
      "term_id": "TERM_cross",
      "name": "Cross",
      "slug": "cross",
      "match_type": "exact_mention",
      "confidence": 1,
      "matched_text": "Cross"
    },
    {
      "term_id": "TERM_dark",
      "name": "Dark",
      "slug": "dark",
      "match_type": "exact_mention",
      "confidence": 1,
      "matched_text": "dark"
    },
    {
      "term_id": "TERM_dead",
      "name": "Dead",
      "slug": "dead",
      "match_type": "exact_mention",
      "confidence": 1,
      "matched_text": "dead"
    },
    {
      "term_id": "TERM_death",
      "name": "Death",
      "slug": "death",
      "match_type": "exact_mention",
      "confidence": 1,
      "matched_text": "death"
    },
    {
      "term_id": "TERM_dialectic",
      "name": "Dialectic",
      "slug": "dialectic",
      "match_type": "exact_mention",
      "confidence": 1,
      "matched_text": "dialectic"
    },
    {
      "term_id": "TERM_does",
      "name": "Does",
      "slug": "does",
      "match_type": "exact_mention",
      "confidence": 1,
      "matched_text": "does"
    },
    {
      "term_id": "TERM_doesn",
      "name": "Doesn",
      "slug": "doesn",
      "match_type": "exact_mention",
      "confidence": 1,
      "matched_text": "doesn"
    },
    {
      "term_id": "TERM_dream",
      "name": "Dream",
      "slug": "dream",
      "match_type": "exact_mention",
      "confidence": 1,
      "matched_text": "dream"
    },
    {
      "term_id": "TERM_eucharist",
      "name": "Eucharist",
      "slug": "eucharist",
      "match_type": "exact_mention",
      "confidence": 1,
      "matched_text": "Eucharist"
    },
    {
      "term_id": "TERM_even",
      "name": "Even",
      "slug": "even",
      "match_type": "exact_mention",
      "confidence": 1,
      "matched_text": "even"
    },
    {
      "term_id": "TERM_eventually",
      "name": "Eventually",
      "slug": "eventually",
      "match_type": "exact_mention",
      "confidence": 1,
      "matched_text": "eventually"
    },
    {
      "term_id": "TERM_everything",
      "name": "Everything",
      "slug": "everything",
      "match_type": "exact_mention",
      "confidence": 1,
      "matched_text": "everything"
    },
    {
      "term_id": "TERM_except",
      "name": "Except",
      "slug": "except",
      "match_type": "exact_mention",
      "confidence": 1,
      "matched_text": "except"
    },
    {
      "term_id": "TERM_finally",
      "name": "Finally",
      "slug": "finally",
      "match_type": "exact_mention",
      "confidence": 1,
      "matched_text": "finally"
    },
    {
      "term_id": "TERM_fish",
      "name": "Fish",
      "slug": "fish",
      "match_type": "exact_mention",
      "confidence": 1,
      "matched_text": "Fish"
    },
    {
      "term_id": "TERM_flux",
      "name": "Flux",
      "slug": "flux",
      "match_type": "exact_mention",
      "confidence": 1,
      "matched_text": "flux"
    },
    {
      "term_id": "TERM_form",
      "name": "Form",
      "slug": "form",
      "match_type": "exact_mention",
      "confidence": 1,
      "matched_text": "form"
    },
    {
      "term_id": "TERM_game",
      "name": "Game",
      "slug": "game",
      "match_type": "exact_mention",
      "confidence": 1,
      "matched_text": "game"
    },
    {
      "term_id": "TERM_gnostic",
      "name": "Gnostic",
      "slug": "gnostic",
      "match_type": "exact_mention",
      "confidence": 1,
      "matched_text": "Gnostic"
    },
    {
      "term_id": "TERM_godhead",
      "name": "Godhead",
      "slug": "godhead",
      "match_type": "exact_mention",
      "confidence": 1,
      "matched_text": "Godhead"
    },
    {
      "term_id": "TERM_golden",
      "name": "Golden",
      "slug": "golden",
      "match_type": "exact_mention",
      "confidence": 1,
      "matched_text": "Golden"
    },
    {
      "term_id": "TERM_golden-fish",
      "name": "Golden Fish",
      "slug": "golden-fish",
      "match_type": "exact_mention",
      "confidence": 1,
      "matched_text": "Golden Fish"
    },
    {
      "term_id": "TERM_greater",
      "name": "Greater",
      "slug": "greater",
      "match_type": "exact_mention",
      "confidence": 1,
      "matched_text": "greater"
    },
    {
      "term_id": "TERM_hagia",
      "name": "Hagia",
      "slug": "hagia",
      "match_type": "exact_mention",
      "confidence": 1,
      "matched_text": "Hagia"
    },
    {
      "term_id": "TERM_hagia-sophia",
      "name": "Hagia Sophia",
      "slug": "hagia-sophia",
      "match_type": "exact_mention",
      "confidence": 1,
      "matched_text": "Hagia Sophia"
    },
    {
      "term_id": "TERM_half",
      "name": "Half",
      "slug": "half",
      "match_type": "exact_mention",
      "confidence": 1,
      "matched_text": "half"
    },
    {
      "term_id": "TERM_handwritten",
      "name": "Handwritten",
      "slug": "handwritten",
      "match_type": "exact_mention",
      "confidence": 1,
      "matched_text": "Handwritten"
    },
    {
      "term_id": "TERM_have",
      "name": "Have",
      "slug": "have",
      "match_type": "exact_mention",
      "confidence": 1,
      "matched_text": "have"
    },
    {
      "term_id": "TERM_having",
      "name": "Having",
      "slug": "having",
      "match_type": "exact_mention",
      "confidence": 1,
      "matched_text": "having"
    },
    {
      "term_id": "TERM_himself",
      "name": "Himself",
      "slug": "himself",
      "match_type": "exact_mention",
      "confidence": 1,
      "matched_text": "himself"
    },
    {
      "term_id": "TERM_holy",
      "name": "Holy",
      "slug": "holy",
      "match_type": "exact_mention",
      "confidence": 1,
      "matched_text": "Holy"
    },
    {
      "term_id": "TERM_holy-spirit",
      "name": "Holy Spirit",
      "slug": "holy-spirit",
      "match_type": "exact_mention",
      "confidence": 1,
      "matched_text": "Holy Spirit"
    },
    {
      "term_id": "TERM_however",
      "name": "However",
      "slug": "however",
      "match_type": "exact_mention",
      "confidence": 1,
      "matched_text": "however"
    },
    {
      "term_id": "TERM_imperial",
      "name": "Imperial",
      "slug": "imperial",
      "match_type": "exact_mention",
      "confidence": 1,
      "matched_text": "Imperial"
    },
    {
      "term_id": "TERM_infinity",
      "name": "Infinity",
      "slug": "infinity",
      "match_type": "exact_mention",
      "confidence": 1,
      "matched_text": "infinity"
    },
    {
      "term_id": "TERM_information",
      "name": "Information",
      "slug": "information",
      "match_type": "exact_mention",
      "confidence": 1,
      "matched_text": "information"
    },
    {
      "term_id": "TERM_into",
      "name": "Into",
      "slug": "into",
      "match_type": "exact_mention",
      "confidence": 1,
      "matched_text": "into"
    },
    {
      "term_id": "TERM_john",
      "name": "John",
      "slug": "john",
      "match_type": "exact_mention",
      "confidence": 1,
      "matched_text": "John"
    },
    {
      "term_id": "TERM_just",
      "name": "Just",
      "slug": "just",
      "match_type": "exact_mention",
      "confidence": 1,
      "matched_text": "just"
    },
    {
      "term_id": "TERM_knowing",
      "name": "Knowing",
      "slug": "knowing",
      "match_type": "exact_mention",
      "confidence": 1,
      "matched_text": "knowing"
    },
    {
      "term_id": "TERM_knowledge",
      "name": "Knowledge",
      "slug": "knowledge",
      "match_type": "exact_mention",
      "confidence": 1,
      "matched_text": "knowledge"
    },
    {
      "term_id": "TERM_like",
      "name": "Like",
      "slug": "like",
      "match_type": "exact_mention",
      "confidence": 1,
      "matched_text": "like"
    },
    {
      "term_id": "TERM_literally",
      "name": "Literally",
      "slug": "literally",
      "match_type": "exact_mention",
      "confidence": 1,
      "matched_text": "literally"
    },
    {
      "term_id": "TERM_long",
      "name": "Long",
      "slug": "long",
      "match_type": "exact_mention",
      "confidence": 1,
      "matched_text": "long"
    },
    {
      "term_id": "TERM_lord",
      "name": "Lord",
      "slug": "lord",
      "match_type": "exact_mention",
      "confidence": 1,
      "matched_text": "Lord"
    },
    {
      "term_id": "TERM_many",
      "name": "Many",
      "slug": "many",
      "match_type": "exact_mention",
      "confidence": 1,
      "matched_text": "many"
    },
    {
      "term_id": "TERM_maya",
      "name": "Maya",
      "slug": "maya",
      "match_type": "exact_mention",
      "confidence": 1,
      "matched_text": "maya"
    },
    {
      "term_id": "TERM_maze",
      "name": "Maze",
      "slug": "maze",
      "match_type": "exact_mention",
      "confidence": 1,
      "matched_text": "maze"
    },
    {
      "term_id": "TERM_mind",
      "name": "Mind",
      "slug": "mind",
      "match_type": "exact_mention",
      "confidence": 1,
      "matched_text": "mind"
    },
    {
      "term_id": "TERM_more",
      "name": "More",
      "slug": "more",
      "match_type": "exact_mention",
      "confidence": 1,
      "matched_text": "more"
    },
    {
      "term_id": "TERM_most",
      "name": "Most",
      "slug": "most",
      "match_type": "exact_mention",
      "confidence": 1,
      "matched_text": "most"
    },
    {
      "term_id": "TERM_much",
      "name": "Much",
      "slug": "much",
      "match_type": "exact_mention",
      "confidence": 1,
      "matched_text": "much"
    },
    {
      "term_id": "TERM_nature",
      "name": "Nature",
      "slug": "nature",
      "match_type": "exact_mention",
      "confidence": 1,
      "matched_text": "nature"
    },
    {
      "term_id": "TERM_nothing",
      "name": "Nothing",
      "slug": "nothing",
      "match_type": "exact_mention",
      "confidence": 1,
      "matched_text": "nothing"
    },
    {
      "term_id": "TERM_only",
      "name": "Only",
      "slug": "only",
      "match_type": "exact_mention",
      "confidence": 1,
      "matched_text": "only"
    },
    {
      "term_id": "TERM_parmenides",
      "name": "Parmenides",
      "slug": "parmenides",
      "match_type": "exact_mention",
      "confidence": 1,
      "matched_text": "Parmenides"
    },
    {
      "term_id": "TERM_part",
      "name": "Part",
      "slug": "part",
      "match_type": "exact_mention",
      "confidence": 1,
      "matched_text": "part"
    },
    {
      "term_id": "TERM_passion",
      "name": "Passion",
      "slug": "passion",
      "match_type": "exact_mention",
      "confidence": 1,
      "matched_text": "Passion"
    },
    {
      "term_id": "TERM_perception",
      "name": "Perception",
      "slug": "perception",
      "match_type": "exact_mention",
      "confidence": 1,
      "matched_text": "perception"
    },
    {
      "term_id": "TERM_perhaps",
      "name": "Perhaps",
      "slug": "perhaps",
      "match_type": "exact_mention",
      "confidence": 1,
      "matched_text": "perhaps"
    },
    {
      "term_id": "TERM_point",
      "name": "Point",
      "slug": "point",
      "match_type": "exact_mention",
      "confidence": 1,
      "matched_text": "point"
    },
    {
      "term_id": "TERM_power",
      "name": "Power",
      "slug": "power",
      "match_type": "exact_mention",
      "confidence": 1,
      "matched_text": "power"
    },
    {
      "term_id": "TERM_purpose",
      "name": "Purpose",
      "slug": "purpose",
      "match_type": "exact_mention",
      "confidence": 1,
      "matched_text": "purpose"
    },
    {
      "term_id": "TERM_real",
      "name": "Real",
      "slug": "real",
      "match_type": "exact_mention",
      "confidence": 1,
      "matched_text": "real"
    },
    {
      "term_id": "TERM_really",
      "name": "Really",
      "slug": "really",
      "match_type": "exact_mention",
      "confidence": 1,
      "matched_text": "really"
    },
    {
      "term_id": "TERM_remember",
      "name": "Remember",
      "slug": "remember",
      "match_type": "exact_mention",
      "confidence": 1,
      "matched_text": "remember"
    },
    {
      "term_id": "TERM_return",
      "name": "Return",
      "slug": "return",
      "match_type": "exact_mention",
      "confidence": 1,
      "matched_text": "return"
    },
    {
      "term_id": "TERM_revelation",
      "name": "Revelation",
      "slug": "revelation",
      "match_type": "exact_mention",
      "confidence": 1,
      "matched_text": "revelation"
    },
    {
      "term_id": "TERM_sankara",
      "name": "Sankara",
      "slug": "sankara",
      "match_type": "exact_mention",
      "confidence": 1,
      "matched_text": "Sankara"
    },
    {
      "term_id": "TERM_seeing",
      "name": "Seeing",
      "slug": "seeing",
      "match_type": "exact_mention",
      "confidence": 1,
      "matched_text": "seeing"
    },
    {
      "term_id": "TERM_seen",
      "name": "Seen",
      "slug": "seen",
      "match_type": "exact_mention",
      "confidence": 1,
      "matched_text": "seen"
    },
    {
      "term_id": "TERM_sein",
      "name": "Sein",
      "slug": "sein",
      "match_type": "exact_mention",
      "confidence": 1,
      "matched_text": "Sein"
    },
    {
      "term_id": "TERM_self",
      "name": "Self",
      "slug": "self",
      "match_type": "exact_mention",
      "confidence": 1,
      "matched_text": "self"
    },
    {
      "term_id": "TERM_sign",
      "name": "Sign",
      "slug": "sign",
      "match_type": "exact_mention",
      "confidence": 1,
      "matched_text": "sign"
    },
    {
      "term_id": "TERM_since",
      "name": "Since",
      "slug": "since",
      "match_type": "exact_mention",
      "confidence": 1,
      "matched_text": "since"
    },
    {
      "term_id": "TERM_something",
      "name": "Something",
      "slug": "something",
      "match_type": "exact_mention",
      "confidence": 1,
      "matched_text": "something"
    },
    {
      "term_id": "TERM_sophia",
      "name": "Sophia",
      "slug": "sophia",
      "match_type": "exact_mention",
      "confidence": 1,
      "matched_text": "Sophia"
    },
    {
      "term_id": "TERM_space",
      "name": "Space",
      "slug": "space",
      "match_type": "exact_mention",
      "confidence": 1,
      "matched_text": "space"
    },
    {
      "term_id": "TERM_spirit",
      "name": "Spirit",
      "slug": "spirit",
      "match_type": "exact_mention",
      "confidence": 1,
      "matched_text": "Spirit"
    },
    {
      "term_id": "TERM_still",
      "name": "Still",
      "slug": "still",
      "match_type": "exact_mention",
      "confidence": 1,
      "matched_text": "still"
    },
    {
      "term_id": "TERM_strange",
      "name": "Strange",
      "slug": "strange",
      "match_type": "exact_mention",
      "confidence": 1,
      "matched_text": "strange"
    },
    {
      "term_id": "TERM_such",
      "name": "Such",
      "slug": "such",
      "match_type": "exact_mention",
      "confidence": 1,
      "matched_text": "such"
    },
    {
      "term_id": "TERM_supper",
      "name": "Supper",
      "slug": "supper",
      "match_type": "exact_mention",
      "confidence": 1,
      "matched_text": "Supper"
    },
    {
      "term_id": "TERM_their",
      "name": "Their",
      "slug": "their",
      "match_type": "exact_mention",
      "confidence": 1,
      "matched_text": "their"
    },
    {
      "term_id": "TERM_these",
      "name": "These",
      "slug": "these",
      "match_type": "exact_mention",
      "confidence": 1,
      "matched_text": "these"
    },
    {
      "term_id": "TERM_things",
      "name": "Things",
      "slug": "things",
      "match_type": "exact_mention",
      "confidence": 1,
      "matched_text": "things"
    },
    {
      "term_id": "TERM_think",
      "name": "Think",
      "slug": "think",
      "match_type": "exact_mention",
      "confidence": 1,
      "matched_text": "think"
    },
    {
      "term_id": "TERM_thought",
      "name": "Thought",
      "slug": "thought",
      "match_type": "exact_mention",
      "confidence": 1,
      "matched_text": "thought"
    },
    {
      "term_id": "TERM_through",
      "name": "Through",
      "slug": "through",
      "match_type": "exact_mention",
      "confidence": 1,
      "matched_text": "through"
    },
    {
      "term_id": "TERM_time",
      "name": "Time",
      "slug": "time",
      "match_type": "exact_mention",
      "confidence": 1,
      "matched_text": "time"
    },
    {
      "term_id": "TERM_true",
      "name": "True",
      "slug": "true",
      "match_type": "exact_mention",
      "confidence": 1,
      "matched_text": "true"
    },
    {
      "term_id": "TERM_truth",
      "name": "Truth",
      "slug": "truth",
      "match_type": "exact_mention",
      "confidence": 1,
      "matched_text": "truth"
    },
    {
      "term_id": "TERM_under",
      "name": "Under",
      "slug": "under",
      "match_type": "exact_mention",
      "confidence": 1,
      "matched_text": "under"
    },
    {
      "term_id": "TERM_universe",
      "name": "Universe",
      "slug": "universe",
      "match_type": "exact_mention",
      "confidence": 1,
      "matched_text": "universe"
    },
    {
      "term_id": "TERM_unless",
      "name": "Unless",
      "slug": "unless",
      "match_type": "exact_mention",
      "confidence": 1,
      "matched_text": "unless"
    },
    {
      "term_id": "TERM_until",
      "name": "Until",
      "slug": "until",
      "match_type": "exact_mention",
      "confidence": 1,
      "matched_text": "until"
    },
    {
      "term_id": "TERM_upon",
      "name": "Upon",
      "slug": "upon",
      "match_type": "exact_mention",
      "confidence": 1,
      "matched_text": "upon"
    },
    {
      "term_id": "TERM_upper",
      "name": "Upper",
      "slug": "upper",
      "match_type": "exact_mention",
      "confidence": 1,
      "matched_text": "upper"
    },
    {
      "term_id": "TERM_valis",
      "name": "Valis",
      "slug": "valis",
      "match_type": "exact_mention",
      "confidence": 1,
      "matched_text": "Valis"
    },
    {
      "term_id": "TERM_very",
      "name": "Very",
      "slug": "very",
      "match_type": "exact_mention",
      "confidence": 1,
      "matched_text": "very"
    },
    {
      "term_id": "TERM_well",
      "name": "Well",
      "slug": "well",
      "match_type": "exact_mention",
      "confidence": 1,
      "matched_text": "well"
    },
    {
      "term_id": "TERM_were",
      "name": "Were",
      "slug": "were",
      "match_type": "exact_mention",
      "confidence": 1,
      "matched_text": "were"
    },
    {
      "term_id": "TERM_whatever",
      "name": "Whatever",
      "slug": "whatever",
      "match_type": "exact_mention",
      "confidence": 1,
      "matched_text": "whatever"
    },
    {
      "term_id": "TERM_white",
      "name": "White",
      "slug": "white",
      "match_type": "exact_mention",
      "confidence": 1,
      "matched_text": "white"
    },
    {
      "term_id": "TERM_whitehead",
      "name": "Whitehead",
      "slug": "whitehead",
      "match_type": "exact_mention",
      "confidence": 1,
      "matched_text": "Whitehead"
    },
    {
      "term_id": "TERM_will",
      "name": "Will",
      "slug": "will",
      "match_type": "exact_mention",
      "confidence": 1,
      "matched_text": "will"
    },
    {
      "term_id": "TERM_wisdom",
      "name": "Wisdom",
      "slug": "wisdom",
      "match_type": "exact_mention",
      "confidence": 1,
      "matched_text": "wisdom"
    },
    {
      "term_id": "TERM_wise",
      "name": "Wise",
      "slug": "wise",
      "match_type": "exact_mention",
      "confidence": 1,
      "matched_text": "Wise"
    },
    {
      "term_id": "TERM_wise-mind",
      "name": "Wise Mind",
      "slug": "wise-mind",
      "match_type": "exact_mention",
      "confidence": 1,
      "matched_text": "Wise Mind"
    },
    {
      "term_id": "TERM_without",
      "name": "Without",
      "slug": "without",
      "match_type": "exact_mention",
      "confidence": 1,
      "matched_text": "without"
    },
    {
      "term_id": "TERM_world",
      "name": "World",
      "slug": "world",
      "match_type": "exact_mention",
      "confidence": 1,
      "matched_text": "world"
    },
    {
      "term_id": "TERM_would",
      "name": "Would",
      "slug": "would",
      "match_type": "exact_mention",
      "confidence": 1,
      "matched_text": "would"
    },
    {
      "term_id": "TERM_acts",
      "name": "Acts",
      "slug": "acts",
      "match_type": "conceptual",
      "confidence": 4,
      "matched_text": "Acts"
    },
    {
      "term_id": "TERM_christ",
      "name": "Christ",
      "slug": "christ",
      "match_type": "conceptual",
      "confidence": 4,
      "matched_text": "Christ"
    },
    {
      "term_id": "TERM_holy-spirit",
      "name": "Holy Spirit",
      "slug": "holy-spirit",
      "match_type": "conceptual",
      "confidence": 4,
      "matched_text": "Holy Spirit"
    },
    {
      "term_id": "TERM_parmenides",
      "name": "Parmenides",
      "slug": "parmenides",
      "match_type": "conceptual",
      "confidence": 4,
      "matched_text": "Parmenides"
    },
    {
      "term_id": "TERM_revelation",
      "name": "Revelation",
      "slug": "revelation",
      "match_type": "conceptual",
      "confidence": 4,
      "matched_text": "Revelation"
    },
    {
      "term_id": "TERM_sophia",
      "name": "Sophia",
      "slug": "sophia",
      "match_type": "conceptual",
      "confidence": 4,
      "matched_text": "Sophia"
    },
    {
      "term_id": "TERM_valis",
      "name": "Valis",
      "slug": "valis",
      "match_type": "conceptual",
      "confidence": 4,
      "matched_text": "VALIS"
    },
    {
      "term_id": "TERM_whitehead",
      "name": "Whitehead",
      "slug": "whitehead",
      "match_type": "conceptual",
      "confidence": 4,
      "matched_text": "Whitehead"
    }
  ],
  "linked_names": [],
  "evidence_excerpts": [
    {
      "text": "-55[Handwritten note on the top margin:]\n\n(So I was right that night when I said to Karen Taylor, \"I saw time slow down, stop + then run backwards\" as a capsule distilating explaining 3-74; when I said it I knew that at last I had it)\n\ncausation; something —I think the Holy Spirit— moved backward in time (I could sense it moving retrograde in time) to cause its own coming into existence in me — any s-f fan who's read time travel stories knows about such paradoxes. I'm saying, no one causes the H",
      "matched_alias": "Sein",
      "term_id": "TERM_sein",
      "term_name": "Sein",
      "term_slug": "sein"
    },
    {
      "text": "-57-\n\n[Handwritten note on the top margin:] (So what originally was a sacrament of Joy has become a comemoration of suffering, sacrifice + death - defeating the whole purpose of the Lord's supper. Because the Spirit does not enter you, of course the sacrament is holy - but pointless.)\n\nThis would correspond with the completion of the macrometasoma. There is such a point as this: its completion. So I am now saying that the construction of the macrometasoma is a representation of the Godhead knowi",
      "matched_alias": "Whitehead",
      "term_id": "TERM_whitehead",
      "term_name": "Whitehead",
      "term_slug": "whitehead"
    }
  ],
  "neighbors": [
    {
      "seg_id": "SEG_EXEG_1978-10-10_SECTION_016_255",
      "title": "1978-10-10_SECTION_016_255.txt",
      "position": 255
    },
    {
      "seg_id": "SEG_EXEG_1978-10-10_SECTION_016_257",
      "title": "1978-10-10_SECTION_016_257.txt",
      "position": 257
    }
  ],
  "document": {
    "title": "Letter",
    "doc_type": "exegesis_section",
    "author": "Philip K. Dick",
    "date_display": "October 10, 1978"
  }
}